odoo/addons/pos_partner_no_create/README.rst
odoo/addons/pos_partner_no_create/__init__.py
odoo/addons/pos_partner_no_create/__manifest__.py
odoo/addons/pos_partner_no_create/i18n/pos_partner_no_create.pot
odoo/addons/pos_partner_no_create/readme/CONTRIBUTORS.rst
odoo/addons/pos_partner_no_create/readme/DESCRIPTION.rst
odoo/addons/pos_partner_no_create/static/description/icon.png
odoo/addons/pos_partner_no_create/static/description/index.html
odoo/addons/pos_partner_no_create/static/src/xml/PartnerListScreen.xml
odoo_addon_pos_partner_no_create-16.0.1.0.0.1.dist-info/METADATA
odoo_addon_pos_partner_no_create-16.0.1.0.0.1.dist-info/WHEEL
odoo_addon_pos_partner_no_create-16.0.1.0.0.1.dist-info/top_level.txt
odoo_addon_pos_partner_no_create-16.0.1.0.0.1.dist-info/RECORD
